{
  "WorkItem": {
    "AffectedComponent": {
      "Name": "",
      "DisplayName": ""
    },
    "ClosedComment": "",
    "ClosedDate": "2011-12-11T20:14:00.77-08:00",
    "CommentCount": 0,
    "Custom": null,
    "Description": "Can you update the filters with the new content (5man, Tier 12-13 and Dragon Soul 10-25man)? \n \nThanks",
    "LastUpdatedDate": "2013-05-16T05:17:15.767-07:00",
    "PlannedForRelease": "",
    "ReleaseVisibleToPublic": false,
    "Priority": {
      "Name": "Low",
      "Severity": 50,
      "Id": 1
    },
    "ProjectName": "Rawr",
    "ReportedDate": "2011-12-05T00:19:28.313-08:00",
    "Status": {
      "Name": "Closed",
      "Id": 4
    },
    "ReasonClosed": {
      "Name": "Unassigned"
    },
    "Summary": "Filters",
    "Type": {
      "Name": "Issue",
      "Id": 3
    },
    "VoteCount": 1,
    "Id": 21870
  },
  "FileAttachments": [
    {
      "FileId": 5467,
      "FileName": "rawr_filters.JPG",
      "DownloadUrl": ".\\5467"
    }
  ],
  "Comments": [
    {
      "Message": "They have been.   I had the same issue.   Use Options -> Reset all caches.    Once it is done, close you browser.   Open it again, load Rawr and you should have all the new filters.\r\n\r\n",
      "PostedDate": "2011-12-05T03:27:54.933-08:00",
      "Id": -2147483648
    },
    {
      "Message": "thanks a lot... i wrote this ticket after the reset all, but i don't have closed the browser :P\r\n\r\nnow works correctly.",
      "PostedDate": "2011-12-05T05:34:39.903-08:00",
      "Id": -2147483648
    },
    {
      "Message": "",
      "PostedDate": "2011-12-11T20:14:00.77-08:00",
      "Id": -2147483648
    },
    {
      "Message": "",
      "PostedDate": "2013-02-21T18:24:04.773-08:00",
      "Id": -2147483648
    },
    {
      "Message": "",
      "PostedDate": "2013-05-16T05:17:15.767-07:00",
      "Id": -2147483648
    }
  ]
}