{
  "WorkItem": {
    "AffectedComponent": {
      "Name": "Rawr.ProtPaladin",
      "DisplayName": "Rawr.ProtPaladin"
    },
    "ClosedComment": "Should be live.",
    "ClosedDate": "2009-11-19T19:04:48.393-08:00",
    "CommentCount": 0,
    "Custom": null,
    "Description": "Currently the default gemming template uses Rare quality gems. Can this be changed to default to Epic quality please.",
    "LastUpdatedDate": "2013-05-16T05:23:49.017-07:00",
    "PlannedForRelease": "",
    "ReleaseVisibleToPublic": false,
    "Priority": {
      "Name": "Low",
      "Severity": 50,
      "Id": 1
    },
    "ProjectName": "Rawr",
    "ReportedDate": "2009-10-17T01:44:53.91-07:00",
    "Status": {
      "Name": "Closed",
      "Id": 4
    },
    "ReasonClosed": {
      "Name": "Unassigned"
    },
    "Summary": "[ProtPaladin] Default Gemming Templates",
    "Type": {
      "Name": "Issue",
      "Id": 3
    },
    "VoteCount": 1,
    "Id": 14454
  },
  "FileAttachments": [],
  "Comments": [
    {
      "Message": "ProtPaladin gemming templates got an overhaul in a recent commit.  Among the changes is the upgrade from rare to epic gems.  It will be available in the next version.",
      "PostedDate": "2009-10-19T09:34:48.913-07:00",
      "Id": -2147483648
    },
    {
      "Message": "",
      "PostedDate": "2009-11-19T19:04:48.393-08:00",
      "Id": -2147483648
    },
    {
      "Message": "",
      "PostedDate": "2010-09-05T16:19:18.103-07:00",
      "Id": -2147483648
    },
    {
      "Message": "",
      "PostedDate": "2013-02-21T18:32:22.67-08:00",
      "Id": -2147483648
    },
    {
      "Message": "",
      "PostedDate": "2013-05-16T05:23:49.017-07:00",
      "Id": -2147483648
    }
  ]
}