{
  "WorkItem": {
    "AffectedComponent": {
      "Name": "Rawr.TankDK",
      "DisplayName": "Rawr.TankDK"
    },
    "ClosedComment": "",
    "ClosedDate": "2009-09-14T14:37:24.24-07:00",
    "CommentCount": 0,
    "Custom": null,
    "Description": "Hi!\n \nI let the optimizer do his work and aimed for maximal Mitiligation Rating.\nNow i got everything enchanted and gemmed like advised but as i tested for the 540 Defense i only got 539 (yes i added an Additional Requirement: Chance to Crit =< 0)\nThe module says i would have 540 Defense at 678 Defense Rating.",
    "LastUpdatedDate": "2017-11-27T11:04:23.897-08:00",
    "PlannedForRelease": "",
    "ReleaseVisibleToPublic": false,
    "Priority": {
      "Name": "Low",
      "Severity": 50,
      "Id": 1
    },
    "ProjectName": "Rawr",
    "ReportedDate": "2009-08-03T10:23:04.83-07:00",
    "Status": {
      "Name": "Closed",
      "Id": 4
    },
    "ReasonClosed": {
      "Name": "Unassigned"
    },
    "Summary": "[TankDK] Defense Rating to Defense",
    "Type": {
      "Name": "Issue",
      "Id": 3
    },
    "VoteCount": 1,
    "Id": 13765
  },
  "FileAttachments": [
    {
      "FileId": 2068,
      "FileName": "Skandi.xml",
      "DownloadUrl": ".\\2068"
    },
    {
      "FileId": 2069,
      "FileName": "Skandi.xml",
      "DownloadUrl": ".\\2069"
    },
    {
      "FileId": 2205,
      "FileName": "ClawTank.xml",
      "DownloadUrl": ".\\2205"
    }
  ],
  "Comments": [
    {
      "Message": "Any PvP gear on?  A smidgeon of Resilience, through a gem, an enchant, a ring, anything?",
      "PostedDate": "2009-08-03T11:49:41.587-07:00",
      "Id": -2147483648
    },
    {
      "Message": "nope",
      "PostedDate": "2009-08-03T14:42:07.523-07:00",
      "Id": -2147483648
    },
    {
      "Message": "It's probably a rounding issue",
      "PostedDate": "2009-08-03T16:53:14.833-07:00",
      "Id": -2147483648
    },
    {
      "Message": "Please post your character as an attachment, and I'll take a look.",
      "PostedDate": "2009-08-03T19:46:30.49-07:00",
      "Id": -2147483648
    },
    {
      "Message": "ty for ur help :)",
      "PostedDate": "2009-08-03T19:54:04.497-07:00",
      "Id": -2147483648
    },
    {
      "Message": "",
      "PostedDate": "2009-08-03T19:54:07.007-07:00",
      "Id": -2147483648
    },
    {
      "Message": "i didnt raid critable so i changes a regal into an enduring at the helmet...",
      "PostedDate": "2009-08-03T19:58:22.693-07:00",
      "Id": -2147483648
    },
    {
      "Message": "",
      "PostedDate": "2009-08-03T19:58:24.317-07:00",
      "Id": -2147483648
    },
    {
      "Message": "",
      "PostedDate": "2009-08-26T09:39:05.167-07:00",
      "Id": -2147483648
    },
    {
      "Message": "",
      "PostedDate": "2009-08-26T12:52:12.793-07:00",
      "Id": -2147483648
    },
    {
      "Message": "The optimizer has done the exact same thing to me with Rawr 2.2.15 (and 2.2.14). It says at 687 def rating i'll have 540 def, but I'm at 539. And i have the chance to crit <= 0 as well. I'll attach my char xml momentarily.",
      "PostedDate": "2009-09-11T17:40:11.687-07:00",
      "Id": -2147483648
    },
    {
      "Message": "My char file.",
      "PostedDate": "2009-09-11T17:49:49.863-07:00",
      "Id": -2147483648
    },
    {
      "Message": "",
      "PostedDate": "2009-09-11T17:49:51.877-07:00",
      "Id": -2147483648
    },
    {
      "Message": "This was fixed in a recent commit, and should be working correctly in the next release.",
      "PostedDate": "2009-09-11T21:56:32.057-07:00",
      "Id": -2147483648
    },
    {
      "Message": "Marking fixed based on the changelist done in the common area.",
      "PostedDate": "2009-09-14T10:43:57.407-07:00",
      "Id": -2147483648
    },
    {
      "Message": "",
      "PostedDate": "2009-09-14T14:37:24.24-07:00",
      "Id": -2147483648
    },
    {
      "Message": "",
      "PostedDate": "2011-05-20T23:39:00.11-07:00",
      "Id": -2147483648
    },
    {
      "Message": "",
      "PostedDate": "2013-02-21T18:33:51.487-08:00",
      "Id": -2147483648
    },
    {
      "Message": "",
      "PostedDate": "2013-05-16T05:25:01.03-07:00",
      "Id": -2147483648
    },
    {
      "Message": "",
      "PostedDate": "2017-11-27T11:04:23.897-08:00",
      "Id": -2147483648
    }
  ]
}