{
  "WorkItem": {
    "AffectedComponent": {
      "Name": "",
      "DisplayName": ""
    },
    "ClosedComment": "Requested before, please search for the extensive conversations already made about this",
    "ClosedDate": "2010-08-28T02:29:27.227-07:00",
    "CommentCount": 0,
    "Custom": null,
    "Description": "Title: Print upgrade list per body slot\nDescription: I often am raiding and don't know if i should roll or pass on items\nSuggestion: It would be nice to be able to get a printable list of upgrade gear with gem slots (as there is often different slots on H and normal mode gear). As the list would be long, it could be broken down in to which body slot it goes (eg head, shoulders, etc). I think this would be useful during raids as sometimes it is hard to know when to roll or pass and rolling has to be done quickly and it is often time consuming and annoying to switch windows to see programs or websites.\n \nWhat do u all think of this?",
    "LastUpdatedDate": "2013-05-16T05:19:58.963-07:00",
    "PlannedForRelease": "",
    "ReleaseVisibleToPublic": false,
    "Priority": {
      "Name": "Low",
      "Severity": 50,
      "Id": 1
    },
    "ProjectName": "Rawr",
    "ReportedDate": "2010-08-28T01:51:54.937-07:00",
    "Status": {
      "Name": "Closed",
      "Id": 4
    },
    "ReasonClosed": {
      "Name": "Unassigned"
    },
    "Summary": "Printable item list for each body slot",
    "Type": {
      "Name": "Issue",
      "Id": 3
    },
    "VoteCount": 1,
    "Id": 18610
  },
  "FileAttachments": [],
  "Comments": []
}