{
  "WorkItem": {
    "AffectedComponent": {
      "Name": "Rawr.Mage",
      "DisplayName": "Rawr.Mage"
    },
    "ClosedComment": "",
    "ClosedDate": "2009-04-02T22:08:38.843-07:00",
    "CommentCount": 0,
    "Custom": null,
    "Description": "I'm trying to use the Optimize feature in b5, and it consistently hangs on the \"equip the findings\" stage. Optimization itself completes OK, but I can't see it's results :) This happens regardless of whether I select Override reenchant/regem and regardless of the thoroughness I set.\n \nI'm using WinXP Home. Please let me know how can I provide more information for you to be able to understand the problem.",
    "LastUpdatedDate": "2017-11-27T11:01:47.083-08:00",
    "PlannedForRelease": "",
    "ReleaseVisibleToPublic": false,
    "Priority": {
      "Name": "Low",
      "Severity": 50,
      "Id": 1
    },
    "ProjectName": "Rawr",
    "ReportedDate": "2009-04-01T12:02:11.787-07:00",
    "Status": {
      "Name": "Closed",
      "Id": 4
    },
    "ReasonClosed": {
      "Name": "Unassigned"
    },
    "Summary": "[Mage] Hangs when using Optimize",
    "Type": {
      "Name": "Issue",
      "Id": 3
    },
    "VoteCount": 1,
    "Id": 12922
  },
  "FileAttachments": [
    {
      "FileId": 1768,
      "FileName": "tel2.xml",
      "DownloadUrl": ".\\1768"
    }
  ],
  "Comments": [
    {
      "Message": "Please attach the character file that this happens with.",
      "PostedDate": "2009-04-01T13:41:51.247-07:00",
      "Id": -2147483648
    },
    {
      "Message": "Here you go.",
      "PostedDate": "2009-04-01T19:58:55.607-07:00",
      "Id": -2147483648
    },
    {
      "Message": "",
      "PostedDate": "2009-04-01T19:58:59.597-07:00",
      "Id": -2147483648
    },
    {
      "Message": "I do optimization fine, it shows the dialog asking if you want to equip, I click yes and it equips it. What exactly is not working for you? Does it crash for you? What is the error you get?",
      "PostedDate": "2009-04-02T12:34:13.077-07:00",
      "Id": -2147483648
    },
    {
      "Message": "I get the dialog, I click yes and the system just hangs, Rawr fully loading the CPU (well, one of its cores). I left it this way overnight, it used up 8 hours of processing time and still didn't complete, so it obviously isn't just \"give it some time to think\". :)",
      "PostedDate": "2009-04-02T21:53:28.74-07:00",
      "Id": -2147483648
    },
    {
      "Message": "Anyway, I re-created my profile from scratch in this build of a program (the one I attached was inherited from 2.1.9), and the optimize->equip routine completes just fine now. So given the fact that I have no error message for you and you can't reproduce the problem on your end, I guess this issue is a dead end - feel free to close :) The only inference to make is that for some reason \"inherited\" profile might not work sometimes.",
      "PostedDate": "2009-04-02T21:56:34.777-07:00",
      "Id": -2147483648
    },
    {
      "Message": "",
      "PostedDate": "2009-04-02T22:08:38.843-07:00",
      "Id": -2147483648
    },
    {
      "Message": "",
      "PostedDate": "2010-09-08T15:32:49.537-07:00",
      "Id": -2147483648
    },
    {
      "Message": "",
      "PostedDate": "2010-09-08T15:34:22.25-07:00",
      "Id": -2147483648
    },
    {
      "Message": "",
      "PostedDate": "2011-03-17T21:30:21.047-07:00",
      "Id": -2147483648
    },
    {
      "Message": "",
      "PostedDate": "2011-05-21T00:00:19.307-07:00",
      "Id": -2147483648
    },
    {
      "Message": "",
      "PostedDate": "2013-02-21T18:35:02.263-08:00",
      "Id": -2147483648
    },
    {
      "Message": "",
      "PostedDate": "2013-05-16T05:25:56.877-07:00",
      "Id": -2147483648
    },
    {
      "Message": "",
      "PostedDate": "2017-11-27T11:01:47.083-08:00",
      "Id": -2147483648
    }
  ]
}