{
  "WorkItem": {
    "AffectedComponent": {
      "Name": "",
      "DisplayName": ""
    },
    "ClosedComment": "ArPharazon fixed this by correcting the link",
    "ClosedDate": "2010-01-04T09:39:49.687-08:00",
    "CommentCount": 0,
    "Custom": null,
    "Description": "Since version 2.3, I'm getting this error message all the time, that says \"Rawr encountered an error while attempting to load a saved image. If you encounter this error multiple times, please ensure that Rawr is unzipped in a location that you have full file read/write access\".\nI have full read/frite access to the folder that Rawr is on, but I still keep getting this message. Previous versions were installed in the same folder, and had no issues",
    "LastUpdatedDate": "2013-05-16T05:23:08.15-07:00",
    "PlannedForRelease": "",
    "ReleaseVisibleToPublic": false,
    "Priority": {
      "Name": "Low",
      "Severity": 50,
      "Id": 1
    },
    "ProjectName": "Rawr",
    "ReportedDate": "2009-12-09T10:08:39.887-08:00",
    "Status": {
      "Name": "Closed",
      "Id": 4
    },
    "ReasonClosed": {
      "Name": "Unassigned"
    },
    "Summary": "Rawr encountered an error while attempting to load a saved image",
    "Type": {
      "Name": "Issue",
      "Id": 3
    },
    "VoteCount": 1,
    "Id": 15267
  },
  "FileAttachments": [],
  "Comments": [
    {
      "Message": "I just had the same problem, and found that a pseudo-fix was to just delete the file it was unable to open. Mine was one of the pet images in the data/talent_images/hunter/pet directory, so I just deleted all of them and it got past the error.\r\nAnd it didn't seem to have any major impact on functionality.",
      "PostedDate": "2009-12-20T14:48:33.537-08:00",
      "Id": -2147483648
    },
    {
      "Message": "The source link for Talent Images is dead now and I don't know what the new one is (or I'd of fixed it by now). Astry has some other grand design where in which to get them, but the code went a little over my head when I tried to implement it.",
      "PostedDate": "2009-12-20T18:30:19.997-08:00",
      "Id": -2147483648
    },
    {
      "Message": "",
      "PostedDate": "2010-01-04T09:39:49.687-08:00",
      "Id": -2147483648
    },
    {
      "Message": "",
      "PostedDate": "2013-02-21T18:31:31.953-08:00",
      "Id": -2147483648
    },
    {
      "Message": "",
      "PostedDate": "2013-05-16T05:23:08.15-07:00",
      "Id": -2147483648
    }
  ]
}