[
  {
    "Id": "126925",
    "ThreadId": "38274",
    "Html": "Do the tanking modules (druid, warrior, paladin) calculate diminishing returns on avoidance stats?<br>\r\n<br>\r\nAlso, armor penetration rating does not seem to be showing up for any items it should nor is it being calculated in dps calculations.&nbsp; Is this a bug or is it something that just hasn't been implemented yet?<br>\r\n",
    "PostedDate": "2008-10-22T08:59:23.117-07:00",
    "UserRole": null,
    "MarkedAsAnswerDate": null
  },
  {
    "Id": "126931",
    "ThreadId": "38274",
    "Html": "Diminishing Returns are calculated, yes.<br>\r\n<br>\r\nArPen Rating is not calculated yet for most models. <br>\r\n",
    "PostedDate": "2008-10-22T09:16:59.323-07:00",
    "UserRole": null,
    "MarkedAsAnswerDate": null
  }
]