[
  {
    "Id": "229126",
    "ThreadId": "67412",
    "Html": "<p>When I use this options, seems rawr try evaluate all piece of gear in database regardless the gear filter I have.</p>\r\n<p>At least in status bar I can see a lot of pieces that isnt selected by actual filter. Can it be changed? Or if it have to evaluate all, can it have a options to change filters AFTER the update list is built?</p>\r\n<p>Some times i want do a lot of lists, like best triumph gear and best conquest gear, and running every time for all is a pain.</p>\r\n<p>&nbsp;</p>\r\n<p>&nbsp;</p>",
    "PostedDate": "2009-08-30T10:54:28-07:00",
    "UserRole": null,
    "MarkedAsAnswerDate": null
  },
  {
    "Id": "229155",
    "ThreadId": "67412",
    "Html": "<p>It should only be considering gear that matches the current filter setting... Sounds like a bug got introduced at some point, I'll look into it.</p>",
    "PostedDate": "2009-08-30T14:06:32.367-07:00",
    "UserRole": null,
    "MarkedAsAnswerDate": null
  }
]