{
  "WorkItem": {
    "AffectedComponent": {
      "Name": "Rawr.DPSWarr",
      "DisplayName": "Rawr.DPSWarr"
    },
    "ClosedComment": "Unable to duplicate even in 2.3.8 release code.",
    "ClosedDate": "2010-02-18T09:59:08.62-08:00",
    "CommentCount": 0,
    "Custom": null,
    "Description": "In the fury module, rawr suggested certain slots with ArP gems and other slots with Str gems, which seems inconsistent - i.e. given the same pieces, either ArP or Str should be suggested for both.  I then looked at the graph and got even crazier results.  The only stat that seems correct is expertise.",
    "LastUpdatedDate": "2013-05-16T05:21:55.273-07:00",
    "PlannedForRelease": "",
    "ReleaseVisibleToPublic": false,
    "Priority": {
      "Name": "Low",
      "Severity": 50,
      "Id": 1
    },
    "ProjectName": "Rawr",
    "ReportedDate": "2010-02-11T11:11:39.48-08:00",
    "Status": {
      "Name": "Closed",
      "Id": 4
    },
    "ReasonClosed": {
      "Name": "Unassigned"
    },
    "Summary": "[DPSWarr] Stat increment providing inconsistent dps increase",
    "Type": {
      "Name": "Issue",
      "Id": 3
    },
    "VoteCount": 1,
    "Id": 16310
  },
  "FileAttachments": [
    {
      "FileId": 2934,
      "FileName": "Rawr 238 Fury Warr Graph.JPG",
      "DownloadUrl": ".\\2934"
    },
    {
      "FileId": 2966,
      "FileName": "Tarkath_Fury.xml",
      "DownloadUrl": ".\\2966"
    },
    {
      "FileId": 2967,
      "FileName": "WhatEbsSees.jpg",
      "DownloadUrl": ".\\2967"
    }
  ],
  "Comments": [
    {
      "Message": "Please add your char file as well",
      "PostedDate": "2010-02-11T11:56:05.993-08:00",
      "Id": -2147483648
    },
    {
      "Message": "Some quick questions (as we do not yet have a character file to look at): Do you have Flooring enabled?  Is your character near the Crit cap?",
      "PostedDate": "2010-02-11T20:29:01.82-08:00",
      "Id": -2147483648
    },
    {
      "Message": "Definitely interesting.  Yes, please attach your saved character xml file, I haven't seen anything like this before.",
      "PostedDate": "2010-02-12T12:47:06.88-08:00",
      "Id": -2147483648
    },
    {
      "Message": "Is this still an issue in 2.3.9?",
      "PostedDate": "2010-02-16T13:36:57.17-08:00",
      "Id": -2147483648
    },
    {
      "Message": "Adding the xml file used to generate that graph.",
      "PostedDate": "2010-02-16T13:54:11.01-08:00",
      "Id": -2147483648
    },
    {
      "Message": "",
      "PostedDate": "2010-02-16T13:54:14.48-08:00",
      "Id": -2147483648
    },
    {
      "Message": "I will check it in 2.3.9 today.",
      "PostedDate": "2010-02-16T13:55:01.74-08:00",
      "Id": -2147483648
    },
    {
      "Message": "",
      "PostedDate": "2010-02-16T13:58:34.643-08:00",
      "Id": -2147483648
    },
    {
      "Message": "The graph seems normal in 2.3.9 with consistent gem recommendations throughout.",
      "PostedDate": "2010-02-16T14:45:52.23-08:00",
      "Id": -2147483648
    },
    {
      "Message": "Opened your file and the issue does not persist\r\n\r\n\n\n** Closed by Jothay 2/16/2010 1:58 PM",
      "PostedDate": "2010-02-16T14:49:24.793-08:00",
      "Id": -2147483648
    },
    {
      "Message": "Re-opening, because even though the bug doesn't occur in 2.3.9, that doesn't mean a bug doesn't still exist elsewhere.  I can't explain this being fixed by our checkins",
      "PostedDate": "2010-02-16T14:49:25.223-08:00",
      "Id": -2147483648
    },
    {
      "Message": "Okay, I've looked at this some more, and I can't duplicate the behavior you're seeing in Rawr 2.3.8 -- my stat graph looks like the attached (WhatEbsSees).  That's the iteration issue that I did fix.\r\n\r\nI'm wondering if you still see your crazy graph if you re-ran Rawr 2.3.8 again (if it was a weird threading issue, we've seen things like that before but they're impossible to track down)",
      "PostedDate": "2010-02-16T15:02:13.79-08:00",
      "Id": -2147483648
    },
    {
      "Message": "",
      "PostedDate": "2010-02-16T15:02:16.68-08:00",
      "Id": -2147483648
    },
    {
      "Message": "",
      "PostedDate": "2010-02-18T09:59:08.62-08:00",
      "Id": -2147483648
    },
    {
      "Message": "",
      "PostedDate": "2010-09-08T16:08:54.537-07:00",
      "Id": -2147483648
    },
    {
      "Message": "",
      "PostedDate": "2013-02-21T18:30:00.027-08:00",
      "Id": -2147483648
    },
    {
      "Message": "",
      "PostedDate": "2013-05-16T05:21:55.273-07:00",
      "Id": -2147483648
    }
  ]
}