{
  "WorkItem": {
    "AffectedComponent": {
      "Name": "Rawr.RestoSham",
      "DisplayName": "Rawr.RestoSham"
    },
    "ClosedComment": "",
    "ClosedDate": "2009-03-11T06:38:24.43-07:00",
    "CommentCount": 0,
    "Custom": null,
    "Description": "At least that's where I think the difference from in game is coming from.  With no gear but talented I'm showing 40 spell power in Rawr and 20 spell power in game.  My talented int is 136 so 20 spell power is the correct number.",
    "LastUpdatedDate": "2013-05-16T05:26:04.213-07:00",
    "PlannedForRelease": "",
    "ReleaseVisibleToPublic": false,
    "Priority": {
      "Name": "Low",
      "Severity": 50,
      "Id": 1
    },
    "ProjectName": "Rawr",
    "ReportedDate": "2009-03-10T15:27:26.18-07:00",
    "Status": {
      "Name": "Closed",
      "Id": 4
    },
    "ReasonClosed": {
      "Name": "Unassigned"
    },
    "Summary": "[RestoSham] Getting double benefit from Nature's Blessing",
    "Type": {
      "Name": "Issue",
      "Id": 3
    },
    "VoteCount": 1,
    "Id": 12787
  },
  "FileAttachments": [],
  "Comments": [
    {
      "Message": "Fixed in most recent build",
      "PostedDate": "2009-03-11T06:38:47.897-07:00",
      "Id": -2147483648
    },
    {
      "Message": "",
      "PostedDate": "2010-09-08T14:57:29.84-07:00",
      "Id": -2147483648
    },
    {
      "Message": "",
      "PostedDate": "2013-02-21T18:35:14.52-08:00",
      "Id": -2147483648
    },
    {
      "Message": "",
      "PostedDate": "2013-05-16T05:26:04.213-07:00",
      "Id": -2147483648
    }
  ]
}