{
  "WorkItem": {
    "AffectedComponent": {
      "Name": "Rawr.Tree",
      "DisplayName": "Rawr.Tree"
    },
    "ClosedComment": "See the help pages on the optimizer before posting issues like this... you have to mark the gems available",
    "ClosedDate": "2009-10-26T14:16:11.883-07:00",
    "CommentCount": 0,
    "Custom": null,
    "Description": "I tried to run an optimization for my tree druid, and found that none of the epic gems were recognized.  I use runed cardinal rubies, luminous ametrines, and purified dreadstones.  It ranked blue items above my ilvl 323 conqueror's leggings because the gems weren't recognized.",
    "LastUpdatedDate": "2017-11-27T11:05:39.82-08:00",
    "PlannedForRelease": "",
    "ReleaseVisibleToPublic": false,
    "Priority": {
      "Name": "Low",
      "Severity": 50,
      "Id": 1
    },
    "ProjectName": "Rawr",
    "ReportedDate": "2009-10-26T14:11:08.177-07:00",
    "Status": {
      "Name": "Closed",
      "Id": 4
    },
    "ReasonClosed": {
      "Name": "Unassigned"
    },
    "Summary": "[Tree] epic gems missing from optimization",
    "Type": {
      "Name": "Issue",
      "Id": 3
    },
    "VoteCount": 1,
    "Id": 14531
  },
  "FileAttachments": [
    {
      "FileId": 2400,
      "FileName": "herb optimization errors.doc",
      "DownloadUrl": ".\\2400"
    }
  ],
  "Comments": []
}