{
  "WorkItem": {
    "AffectedComponent": {
      "Name": "Rawr.Warlock",
      "DisplayName": "Rawr.Warlock"
    },
    "ClosedComment": "Added in changeset 44598.",
    "ClosedDate": "2009-12-30T18:37:49.287-08:00",
    "CommentCount": 0,
    "Custom": null,
    "Description": "The Glyph of Quick Decay which was newly added in 3.3 is missing from the Warlock model.\n \nhttp://www.wowhead.com/?item=50077\n \nThe issues regarding Warlock haste would probably have to be addressed before the implementation, ALSO, the hotfixing that are incoming to ROLLING CORRUPTION haste might change the implementation of this as well.",
    "LastUpdatedDate": "2013-05-16T05:23:04.437-07:00",
    "PlannedForRelease": "",
    "ReleaseVisibleToPublic": false,
    "Priority": {
      "Name": "Low",
      "Severity": 50,
      "Id": 1
    },
    "ProjectName": "Rawr",
    "ReportedDate": "2009-12-11T12:33:39.99-08:00",
    "Status": {
      "Name": "Closed",
      "Id": 4
    },
    "ReasonClosed": {
      "Name": "Unassigned"
    },
    "Summary": "[Warlock] Glyph of Quick Decay missing",
    "Type": {
      "Name": "Issue",
      "Id": 3
    },
    "VoteCount": 4,
    "Id": 15367
  },
  "FileAttachments": [],
  "Comments": [
    {
      "Message": "ArPharazon should be releasing a major update to the Warlock module in the next day or two, so we will see what he has in store.",
      "PostedDate": "2009-12-11T15:52:52.327-08:00",
      "Id": -2147483648
    },
    {
      "Message": "",
      "PostedDate": "2009-12-14T05:04:06.86-08:00",
      "Id": -2147483648
    },
    {
      "Message": "The rolling corruption has been addressed already. This glyph effects more then just Affliction warlocks, so please consider this as a gesture of good faith towards your beloved Warlocks :)",
      "PostedDate": "2009-12-14T05:05:44.607-08:00",
      "Id": -2147483648
    },
    {
      "Message": "The rolling corruption has been addressed already. This glyph effects more then just Affliction warlocks, so please consider this as a gesture of good faith towards your beloved Warlocks :)",
      "PostedDate": "2009-12-14T05:05:47.873-08:00",
      "Id": -2147483648
    },
    {
      "Message": "",
      "PostedDate": "2009-12-14T16:12:05.72-08:00",
      "Id": -2147483648
    },
    {
      "Message": "",
      "PostedDate": "2009-12-28T23:27:35.663-08:00",
      "Id": -2147483648
    },
    {
      "Message": "",
      "PostedDate": "2009-12-30T18:37:49.287-08:00",
      "Id": -2147483648
    },
    {
      "Message": "",
      "PostedDate": "2010-09-05T14:51:23.21-07:00",
      "Id": -2147483648
    },
    {
      "Message": "",
      "PostedDate": "2010-09-05T14:51:59.277-07:00",
      "Id": -2147483648
    },
    {
      "Message": "",
      "PostedDate": "2011-03-17T20:42:11.687-07:00",
      "Id": -2147483648
    },
    {
      "Message": "",
      "PostedDate": "2013-02-21T18:31:27.283-08:00",
      "Id": -2147483648
    },
    {
      "Message": "",
      "PostedDate": "2013-05-16T05:23:04.437-07:00",
      "Id": -2147483648
    }
  ]
}