{
  "WorkItem": {
    "AffectedComponent": {
      "Name": "Rawr.RestoSham",
      "DisplayName": "Rawr.RestoSham"
    },
    "ClosedComment": "Fixed in changeset 50730.",
    "ClosedDate": "2010-05-21T23:47:51.08-07:00",
    "CommentCount": 0,
    "Custom": null,
    "Description": "Both are only available for Ele spec not for resto. When i switch spec i can choose them from the list but not when i have resto spec. Professions are set right. They show up correctly in the loaded char items but are not available to choose in the enchants list (while springy arachnowave is) when i want them for optimizer.",
    "LastUpdatedDate": "2013-05-16T05:20:42.567-07:00",
    "PlannedForRelease": "",
    "ReleaseVisibleToPublic": false,
    "Priority": {
      "Name": "Low",
      "Severity": 50,
      "Id": 1
    },
    "ProjectName": "Rawr",
    "ReportedDate": "2010-05-18T02:05:30.593-07:00",
    "Status": {
      "Name": "Closed",
      "Id": 4
    },
    "ReasonClosed": {
      "Name": "Unassigned"
    },
    "Summary": "[RestoSham] Lightweave Embroidery and Hyperspeed Accelerators Missing",
    "Type": {
      "Name": "Issue",
      "Id": 3
    },
    "VoteCount": 1,
    "Id": 17716
  },
  "FileAttachments": [],
  "Comments": [
    {
      "Message": "I'll need to know which version you are using as well as a posting of your character file so I can make sure to reproduce what you are seeing.",
      "PostedDate": "2010-05-21T17:34:35.327-07:00",
      "Id": -2147483648
    },
    {
      "Message": "",
      "PostedDate": "2010-05-21T23:47:51.08-07:00",
      "Id": -2147483648
    },
    {
      "Message": "",
      "PostedDate": "2013-02-21T18:28:26.9-08:00",
      "Id": -2147483648
    },
    {
      "Message": "",
      "PostedDate": "2013-05-16T05:20:42.567-07:00",
      "Id": -2147483648
    }
  ]
}