{
  "WorkItem": {
    "AffectedComponent": {
      "Name": "Rawr.Warlock",
      "DisplayName": "Rawr.Warlock"
    },
    "ClosedComment": "Old version of Rawr.Warlock",
    "ClosedDate": "2009-03-17T04:53:01.453-07:00",
    "CommentCount": 0,
    "Custom": null,
    "Description": "I think immolate is not calculated correctly. I loaded my warlock from the armory and I saw the immolate stats: min hit 56, max hit 113. But that's not right,  it hits for ~500 with my warlock. In addition, I know my dps raises with immolate in the cycle, but in Rawr my dps goes down...",
    "LastUpdatedDate": "2013-05-16T05:27:14.713-07:00",
    "PlannedForRelease": "",
    "ReleaseVisibleToPublic": false,
    "Priority": {
      "Name": "Low",
      "Severity": 50,
      "Id": 1
    },
    "ProjectName": "Rawr",
    "ReportedDate": "2008-05-28T05:08:40.57-07:00",
    "Status": {
      "Name": "Closed",
      "Id": 4
    },
    "ReasonClosed": {
      "Name": "Unassigned"
    },
    "Summary": "[Warlock] Immolate Bug",
    "Type": {
      "Name": "Issue",
      "Id": 3
    },
    "VoteCount": 1,
    "Id": 10251
  },
  "FileAttachments": [],
  "Comments": []
}